setup.cfg
setup.py
ysy/Devil.py
ysy/__init__.py
ysy.egg-info/PKG-INFO
ysy.egg-info/SOURCES.txt
ysy.egg-info/dependency_links.txt
ysy.egg-info/top_level.txt