Metadata-Version: 2.2
Name: ysy
Version: 2.1
Summary: KH
Author: NASR
Author-email: nasr2python@gmail.com
Classifier: Programming Language :: Python :: 3
Classifier: License :: OSI Approved :: MIT License
Classifier: Operating System :: OS Independent
Dynamic: author
Dynamic: author-email
Dynamic: classifier
Dynamic: summary
